[
    {"Semester":"Semester 1", "Semester_Start_Date": "01/08/2020", "Semester_End_Date": "31/12/2020", "Passing_status": "Passed", "Status": "Paid"},
    {"Semester":"Semester 2", "Semester_Start_Date": "01/01/2021", "Semester_End_Date": "31/07/2021", "Passing_status": "Passed", "Status": "Paid"},
    {"Semester":"Semester 3", "Semester_Start_Date": "01/08/2021", "Semester_End_Date": "31/01/2021", "Passing_status": "Passed", "Status": "Paid"},
    {"Semester":"Semester 4", "Semester_Start_Date": "01/01/2022", "Semester_End_Date": "31/06/2021", "Passing_status": "Passed", "Status": "Paid"},
    {"Semester":"Semester 5", "Semester_Start_Date": "", "Semester_End_Date": "", "Passing_status": "Not Enrolled", "Status": "Pending"},
    {"Semester":"Semester 6", "Semester_Start_Date": "", "Semester_End_Date": "", "Passing_status": "Not Enrolled", "Status": "Pending"},
    {"Semester":"Semester 7", "Semester_Start_Date": "", "Semester_End_Date": "", "Passing_status": "Not Enrolled", "Status": "Pending"},
    {"Semester":"Semester 8", "Semester_Start_Date": "", "Semester_End_Date": "", "Passing_status": "Not Enrolled", "Status": "Pending"}
]
